{
  "住所": "大阪府堺市堺区永代町５丁１番１２号",
  "Twitter": "",
  "Facebook": "",
  "Instagram": "",
  "創業年": "",
  "法人名": "株式会社イシン",
  "紹介文": "",
  "アイコン": "",
  "事業概要": "",
  "代表者名": "宋磊",
  "取扱商品": "",
  "営業品目": null,
  "従業員数": "",
  "採用予定": "予定有り",
  "更新日時": "2021-12-09T15:53:53.572+00:00",
  "法人番号": "1120101062554",
  "特許情報": "",
  "背景画像": "",
  "表彰情報": "",
  "電話番号": "072-275-4065",
  "代表の写真": "",
  "取引先業種": "",
  "設備と技術": "",
  "設立年月日": "2020-10-28",
  "法人名(カナ)": "イシン",
  "企業規模詳細": "",
  "キャッチコピー": "",
  "企業紹介画像①": "",
  "企業紹介画像②": "",
  "企業紹介画像③": "",
  "届出・認定情報": "",
  "セールスポイント": "",
  "企業ホームページ": "",
  "店舗・事業所情報": "[]",
  "主な商品・サービス": "",
  "他社との連携を考える事業": ""
}