{
  "住所": "大阪府堺市西区上野芝町８丁２２番５－３号",
  "Twitter": "madaikenkyujyo",
  "Facebook": "",
  "Instagram": "madaikenkyujyo",
  "創業年": "2010年4月",
  "法人名": "株式会社夢志堂",
  "紹介文": "",
  "アイコン": "https://img.sakacil.com/data/20220822/c03b5686-511c-458d-a627-4fedb888ce61.jpg",
  "事業概要": "愛媛県の愛南町の真鯛を使った、お昼は「鯛出汁ラーメン」と「鯛めし」を提供するラーメン屋。夜は真鯛専門居酒屋の二毛作店舗を経営する飲食業を営む会社です。",
  "代表者名": "津布久照慶",
  "取扱商品": "真鯛",
  "営業品目": "7699",
  "従業員数": "",
  "採用予定": "予定有り",
  "更新日時": "2022-08-22T02:42:17.563+00:00",
  "法人番号": "1120101035972",
  "特許情報": "商標登録「真鯛研究所」",
  "背景画像": "https://img.sakacil.com/data/20220822/caffac8f-5cb4-4503-bf4e-d09a8e22e2a6.jpg",
  "表彰情報": "",
  "電話番号": "090-8823-2402",
  "代表の写真": "",
  "取引先業種": "水産業",
  "設備と技術": "",
  "設立年月日": "2011-12-26",
  "法人名(カナ)": "カブシキカイシャユメシドウ",
  "企業規模詳細": "",
  "キャッチコピー": "",
  "企業紹介画像①": "https://img.sakacil.com/data/20220822/da669d34-5d08-4acf-84e7-ba3c32db3169.GIF",
  "企業紹介画像②": "https://img.sakacil.com/data/20220822/b9730df5-3c17-489a-85cd-8406c8c24b85.JPG",
  "企業紹介画像③": "https://img.sakacil.com/data/20220822/4ed861c2-6ea4-4dbc-a477-1ebfe9c9858f.jpg",
  "届出・認定情報": "",
  "セールスポイント": "愛南町の真鯛を使った、「鯛出汁ラーメン」真鯛を使った料理の提供！現在フランチャイズオーナー募集！",
  "企業ホームページ": "https://madaikenkyujyo.jimadosite.com",
  "店舗・事業所情報": "[{\"名称\":\"真鯛研究所\",\"名称(カナ)\":\"マダイケンキュウジョ\",\"住所\":\"大阪府堺市西区浜寺石津町西4-1-1\",\"営業曜日\":\"定休日「月曜日」\",\"営業開始時間\":\"11:45\",\"営業終了時間\":\"23:00\",\"営業日備考\":\"14：00～17：00迄は夜営業の準備の為、営業しておりません。\",\"WebサイトURL\":\"\"}]",
  "主な商品・サービス": "鯛出汁ラーメン",
  "他社との連携を考える事業": "農林水産業"
}