{
  "住所": "大阪府堺市中区東山８０３番地",
  "Twitter": "",
  "Facebook": "",
  "Instagram": "",
  "創業年": "",
  "法人名": "南海ウイングバス金岡株式会社",
  "紹介文": "",
  "アイコン": "",
  "事業概要": "",
  "代表者名": "",
  "取扱商品": "",
  "営業品目": "H",
  "従業員数": "",
  "採用予定": "",
  "更新日時": "2022-10-12T06:48:56.930+00:00",
  "法人番号": "2120101008647",
  "特許情報": "",
  "背景画像": "",
  "表彰情報": "",
  "電話番号": "",
  "代表の写真": "",
  "取引先業種": "",
  "設備と技術": "",
  "設立年月日": "",
  "法人名(カナ)": "ナンカイウイングバスカナオカ",
  "企業規模詳細": "",
  "キャッチコピー": "",
  "企業紹介画像①": "",
  "企業紹介画像②": "",
  "企業紹介画像③": "",
  "届出・認定情報": "",
  "セールスポイント": "",
  "企業ホームページ": "http://www.nankaibus.jp/",
  "店舗・事業所情報": "[]",
  "主な商品・サービス": "",
  "他社との連携を考える事業": ""
}