{
  "住所": "大阪府堺市美原区大保２１５番地",
  "Twitter": "",
  "Facebook": "",
  "Instagram": "",
  "創業年": "",
  "法人名": "有限会社北新工業",
  "紹介文": "",
  "アイコン": "",
  "事業概要": "プレス加工全般、大物プレス、順送、ロボットライン、単発プレス、異形物の絞り、板鍛造、その他\n図面立ち上げから試作、金型作成、プレス製造、タップ、カシメ、洗浄機による仕上げから梱包まで。（溶接、鍍金、塗装、組立ては協力企業にて対応）",
  "代表者名": "新田　典彦",
  "取扱商品": "（取扱商品）産業機器　家電製品　空調　ガス　エコキュート　その他\n（使用材料）SUS　銅　A/L　カラー鋼板　表面処理材　特殊鋼　他",
  "営業品目": null,
  "従業員数": "38人",
  "採用予定": "",
  "更新日時": "2021-11-22T15:30:58.174+00:00",
  "法人番号": "2120102013646",
  "特許情報": "特許登録(トイレットペーパー保持体)　実用新案１件　ISO9001 環境エコアクション21(14000相当)　経営革新計画　経営力向上計画　BCP事業継続計画",
  "背景画像": "",
  "表彰情報": "",
  "電話番号": "072-369-2286",
  "代表の写真": "",
  "取引先業種": "家電メーカー　産業機器メーカー　遮断機メーカー　空調メーカー　ガス機器メーカー　自動車メーカー　その他 ",
  "設備と技術": "60ｔから150ｔによる単発10連ライン。大型プレス8台による複数工程。順送ライン（材巾600まで）やロボットライン（同2000まで）など工程の最適化を図り、タップ、カシメ、洗浄、梱包まで責任ある一貫生産でQCDを実現。",
  "設立年月日": "",
  "法人名(カナ)": "ホクシンコウギョウ",
  "企業規模詳細": "",
  "キャッチコピー": "",
  "企業紹介画像①": "",
  "企業紹介画像②": "",
  "企業紹介画像③": "",
  "届出・認定情報": "",
  "セールスポイント": "弊社はプレス加工に特化した会社です。加工領域が広く、絞り物、外観品機能部品から特殊材の加工まで、量産品をはじめ多品種、少量品も多く受注しております。あらゆる業界のプレス品の受注により永年培ってまいりました経験や知識、技術をもとに製造プロセスの見直し、工程短縮、コスト低減などの提案を得意としております。",
  "企業ホームページ": "http://hokushin-kougyo.co.jp/",
  "店舗・事業所情報": [],
  "主な商品・サービス": "プレス加工全般。他社が断る難加工の鋼種材の加工、外周ヘミング品の順送加工、異形物の絞り、板鍛造、また、切削品のプレス化や順送型内の複合加工などVA.VE事例が豊富です",
  "他社との連携を考える事業": ""
}