{
  "住所": "大阪府堺市北区中百舌鳥町６丁９５６番地の２",
  "Twitter": "",
  "Facebook": "",
  "Instagram": "",
  "創業年": "1963年",
  "法人名": "有限会社サン鉄工",
  "紹介文": "当社はお客様の要望に真摯に向き合い、妥協しない品質と迅速な対応によって、お客様のニーズを最優先に考えます。どんなプロジェクトでも心を込めて対応し、お客様の満足を追求します。",
  "アイコン": "https://img.sakacil.com/data/20230829/0b4112ba-22a1-45f7-8f74-27d1994a2ab9.jpg",
  "事業概要": "金属の精密切削加工",
  "代表者名": "小林　隆一",
  "取扱商品": "半導体製造装置部品等金属加工品",
  "営業品目": "2663",
  "従業員数": "6人",
  "採用予定": "予定有り",
  "更新日時": "2023-08-29T15:36:10.535+09:00",
  "法人番号": "3120102002144",
  "特許情報": "",
  "背景画像": "",
  "表彰情報": "",
  "電話番号": "072-257-3565",
  "代表の写真": "",
  "取引先業種": "半導体製造装置メーカー　製菓機械メーカー　産業機械メーカー",
  "設備と技術": "立型MC×４　立型フライス盤×３　汎用旋盤　NC旋盤　平面研削盤などの設備があります。 ",
  "設立年月日": "1990-03-01",
  "法人名(カナ)": "ユウゲンガイシャサンテッコウ",
  "企業規模詳細": "男性５名　女性１名",
  "キャッチコピー": "信頼と共に成長する",
  "企業紹介画像①": "https://img.sakacil.com/data/20230829/9b71c645-9cac-4786-acf5-a446405e0f39.jpg",
  "企業紹介画像②": "",
  "企業紹介画像③": "",
  "届出・認定情報": "",
  "セールスポイント": "あらゆる金属の精密切削加工　単品から中量まで対応します。 また協力会社にて0.2㎜から20ｍまでの加工に対応できます。",
  "企業ホームページ": "http://切削加工.com",
  "店舗・事業所情報": "[]",
  "主な商品・サービス": "",
  "他社との連携を考える事業": ""
}