{
  "住所": "大阪府堺市堺区宿屋町東３丁３番２２号",
  "Twitter": "",
  "Facebook": "",
  "Instagram": "",
  "創業年": "1916年",
  "法人名": "株式会社馬場刄物製作所",
  "紹介文": "",
  "アイコン": "https://img.sakacil.com/data/20211211/ff746b67-8a86-447a-883c-fcc5aa00e8b1.jpeg",
  "事業概要": "刃物、 家庭用品　家庭用、 業務用包丁の製造・卸　品質管理、 オリジナリティーの高い製造に重点を置いております。 ",
  "代表者名": "馬場　修三",
  "取扱商品": "包丁、まな板、砥石など",
  "営業品目": "2429",
  "従業員数": "7人",
  "採用予定": "",
  "更新日時": "2021-12-13T10:00:46.905+00:00",
  "法人番号": "3120101006113",
  "特許情報": "",
  "背景画像": "https://img.sakacil.com/data/20211211/df10d94d-c841-4087-944e-beb9b0c74a5f.png",
  "表彰情報": "",
  "電話番号": "072-232-2641",
  "代表の写真": "",
  "取引先業種": "通販・生協",
  "設備と技術": "",
  "設立年月日": "",
  "法人名(カナ)": "カブシキガイシャババハモノセイサクジョ",
  "企業規模詳細": "",
  "キャッチコピー": "",
  "企業紹介画像①": "",
  "企業紹介画像②": "",
  "企業紹介画像③": "https://img.sakacil.com/data/20211213/0c2931da-ab8a-46e3-9587-ce98e8ccbea2.jpeg",
  "届出・認定情報": "",
  "セールスポイント": "オリジナリティーの高い商品。 ソフト面でもいろいろな提案が可能です。 ",
  "企業ホームページ": "www.baba-hamono.com",
  "店舗・事業所情報": "[]",
  "主な商品・サービス": "",
  "他社との連携を考える事業": ""
}