{
  "法人番号": "4120001221232",
  "法人名": "株式会社ウェイバック",
  "法人名(カナ)": "ウェイバック",
  "住所": "大阪府堺市堺区中瓦町２丁３－２０矢本ビル３Ｆ",
  "代表の写真": "",
  "代表者名": "上辻　勇",
  "キャッチコピー": "WEBに関する 事業は弊社に全て お任せください",
  "紹介文": "DX化が加速し、IT人材の確保からマーケティングや開発のノウハウが求められる多様性の時代になりました。IT・WEB・DXに関する事なら何でもご相談ください。弊社がこれまで培ったノウハウをベースに全力で御社を支援致します。",
  "アイコン": "",
  "背景画像": "https://img.sakacil.com/data/20211213/8828b268-bec6-4d02-97a1-d063e8fe9aae.jpeg",
  "企業紹介画像①": "",
  "企業紹介画像②": "",
  "企業紹介画像③": "",
  "Facebook": "https://m.facebook.com/waybackosaka/",
  "Instagram": "",
  "Twitter": "https://twitter.com/wayback_uetsuji",
  "従業員数": "3人",
  "企業規模詳細": "男性：1人、女性：2人",
  "設立年月日": "2019-05-22",
  "創業年": "2019年5月22日",
  "営業品目": "9299",
  "事業概要": "広告運用、メディア運営、マーケティングの専門家として\nWEBに関するあらゆるニーズに対応いたします。",
  "企業ホームページ": "https://wayback.co.jp/",
  "電話番号": "080-2595-1134",
  "採用予定": "未定",
  "特許情報": "商標の件数：1件",
  "届出・認定情報": "",
  "表彰情報": "",
  "取扱商品": "",
  "取引先業種": "",
  "他社との連携を考える事業": "",
  "主な商品・サービス": "レンタルジム「PSGYM」、Integrey Gaming",
  "設備と技術": "",
  "店舗・事業所情報": "[]",
  "セールスポイント": "",
  "更新日時": "2021-12-13T05:13:48.981+00:00"
}