{
  "住所": "大阪府堺市東区八下町１丁１４２番地",
  "Twitter": "",
  "Facebook": "",
  "Instagram": "",
  "創業年": "",
  "法人名": "広栄イワサキ株式会社",
  "紹介文": "",
  "アイコン": "",
  "事業概要": "業務用厨房製品（ステンレス）\n学校用調理実習台、流し台\n排気フード、給排気フード、フィルターボックス、空調機材、薬品庫の製造販売",
  "代表者名": "岩崎　浩賜",
  "取扱商品": "キャビネット\nシンク\n空調関連",
  "営業品目": null,
  "従業員数": "35人",
  "採用予定": "",
  "更新日時": "2021-11-22T15:46:04.026+00:00",
  "法人番号": "4120101002128",
  "特許情報": "",
  "背景画像": "",
  "表彰情報": "",
  "電話番号": "072-252-0262",
  "代表の写真": "",
  "取引先業種": "学校等公共施設 工場、飲食店",
  "設備と技術": "NCタレットパンチプレス、シャーリングマシン、プレスブレーキ",
  "設立年月日": "",
  "法人名(カナ)": "コウエイイワサキ",
  "企業規模詳細": "",
  "キャッチコピー": "",
  "企業紹介画像①": "",
  "企業紹介画像②": "",
  "企業紹介画像③": "",
  "届出・認定情報": "",
  "セールスポイント": "創業以来のノウハウによりお客様にご満足いただける高品質の製品をご提供しております。製品についてはもちろん図面や材料についてもお問い合わせください。",
  "企業ホームページ": "",
  "店舗・事業所情報": [],
  "主な商品・サービス": "CAD図面作成から保管納品まで一貫した請け負いサービス",
  "他社との連携を考える事業": ""
}