{
  "住所": "大阪府堺市西区菱木２丁２１７２番地１４",
  "Twitter": "",
  "Facebook": "",
  "Instagram": "",
  "創業年": "",
  "法人名": "株式会社コートク",
  "紹介文": "",
  "アイコン": "",
  "事業概要": "",
  "代表者名": "辻川勝彦",
  "取扱商品": "",
  "営業品目": null,
  "従業員数": "",
  "採用予定": "",
  "更新日時": "2021-12-10T06:02:36.835+00:00",
  "法人番号": "5120101053376",
  "特許情報": "",
  "背景画像": "",
  "表彰情報": "",
  "電話番号": "",
  "代表の写真": "",
  "取引先業種": "",
  "設備と技術": "",
  "設立年月日": "",
  "法人名(カナ)": "コートク",
  "企業規模詳細": "",
  "キャッチコピー": "",
  "企業紹介画像①": "",
  "企業紹介画像②": "",
  "企業紹介画像③": "",
  "届出・認定情報": "",
  "セールスポイント": "",
  "企業ホームページ": "",
  "店舗・事業所情報": "[]",
  "主な商品・サービス": "",
  "他社との連携を考える事業": ""
}