{
  "住所": "大阪府堺市美原区今井３９９番６",
  "Twitter": "",
  "Facebook": "",
  "Instagram": "",
  "創業年": "",
  "法人名": "タカギ産業株式会社",
  "紹介文": "",
  "アイコン": "",
  "事業概要": "・業務用食品容器（事業所、幼稚園、メディカル、福祉介護用在宅配色）の製造・販売\n・その他食品業界に関わる商品販売",
  "代表者名": "髙木　雅之",
  "取扱商品": "・業務用ポリプロピレン製食器\n・使い捨て容器（PS、PPF、OPS、HIPS）\n・メラミン食器、漆器\n・消耗品副資材（紙カップ、フィルムカップ、アルミカップ、バラン、割りばし、衛生商品）\n・コンテナ・厨房用品（鍋、フライパン、炊飯器、温蔵庫、台車）",
  "営業品目": null,
  "従業員数": "46人",
  "採用予定": "",
  "更新日時": "2021-11-23T07:46:45.975+00:00",
  "法人番号": "6120101021613",
  "特許情報": "意匠 6件（弁当用容器 / 弁当用包装容器 / 弁当用包装容器の蓋 / 弁当容器用シート / 包装用容器 他）",
  "背景画像": "",
  "表彰情報": "",
  "電話番号": "072-362-3281",
  "代表の写真": "",
  "取引先業種": "産業給食会社、食品製造メーカー",
  "設備と技術": "",
  "設立年月日": "",
  "法人名(カナ)": "タカギサンギョウ",
  "企業規模詳細": "",
  "キャッチコピー": "",
  "企業紹介画像①": "",
  "企業紹介画像②": "",
  "企業紹介画像③": "",
  "届出・認定情報": "",
  "セールスポイント": "業務用ポリプロピレン食器では業界トップシャエを獲得しており、レンジ対応容器など時代に合わせた新商品開発や企画、デザイン、金型作製を自社工場で試作、生産、販売まで一括管理販売をしています。多様化するニーズに的確に応える金型作製技術、成型技術で多くのお客様から高い評価をいただいております。",
  "企業ホームページ": "http://www.mc-takagi.co.jp",
  "店舗・事業所情報": [],
  "主な商品・サービス": "・業務用ポリプロピレン製食器 ・食品業界、食品会社に関わる副資材",
  "他社との連携を考える事業": ""
}