{
  "法人番号": "7120101004773",
  "法人名": "田中ステンレス株式会社",
  "法人名(カナ)": "",
  "住所": "大阪府堺市中区大野芝町１４９番地の５",
  "代表の写真": "",
  "代表者名": "田中　辰夫",
  "キャッチコピー": "",
  "紹介文": "",
  "アイコン": "",
  "背景画像": "",
  "企業紹介画像①": "",
  "企業紹介画像②": "",
  "企業紹介画像③": "",
  "Facebook": "",
  "Instagram": "",
  "Twitter": "",
  "従業員数": "20人",
  "企業規模詳細": "",
  "設立年月日": "",
  "創業年": "",
  "営業品目": null,
  "事業概要": "金属加工全般（ステンレス・鉄・アルミなど）",
  "企業ホームページ": "www.tanaka-stn.co.jp",
  "電話番号": "072-235-6563",
  "採用予定": "",
  "特許情報": "",
  "届出・認定情報": "",
  "表彰情報": "",
  "取扱商品": "ステンレス製品が主",
  "取引先業種": "①トラック販売会社（ディーラー）②トラック用品販売ショップ③電気機器設備④機械メーカー⑤建築業者",
  "他社との連携を考える事業": "",
  "主な商品・サービス": "トラック架装用品（フロントバイザー、 フェンダー、 テールステー等）精密板金",
  "設備と技術": "①レーザー加工機②レーザー・タレパン複合機③NCベンダー④TIG溶接⑤半自動溶接⑥薄板の溶接（0.3～6㎜）ファイバー溶接機",
  "店舗・事業所情報": [],
  "セールスポイント": "小量・多品種に対応　試作・短納期。 多量品種（量産品）も対応。 ",
  "更新日時": "2021-11-22T15:11:31.400+00:00"
}