{
  "住所": "大阪府堺市堺区材木町西２丁１番２９号",
  "Twitter": "",
  "Facebook": "",
  "Instagram": "",
  "創業年": "",
  "法人名": "株式会社薫明堂",
  "紹介文": "線香の製法は、今より約400年前、中国の明の時代に貿易港として栄えた堺に伝わりました。\n弊社は、文化年間（約200年前）に創業し、以来、伝統の技術を磨き、常に創意と工夫をこらし、薫物の配合に研究を重ねて今日に至りました。\n現在、全国でご愛顧頂いております弊社の製品は、約220品にのぼり、そのひとつひとつに、長年の努力と成果が実っているものと自負いたしております。\n何卒、その真価をお認めいただき、末永くご愛顧賜りますようお願い申し上げます。",
  "アイコン": "",
  "事業概要": "",
  "代表者名": "",
  "取扱商品": "",
  "営業品目": null,
  "従業員数": "",
  "採用予定": "",
  "更新日時": "2022-09-15T00:41:07.571+00:00",
  "法人番号": "8120101002025",
  "特許情報": "",
  "背景画像": "",
  "表彰情報": "",
  "電話番号": "072-229-6662",
  "代表の写真": "",
  "取引先業種": "",
  "設備と技術": "",
  "設立年月日": "",
  "法人名(カナ)": "クンメイドウ",
  "企業規模詳細": "",
  "キャッチコピー": "",
  "企業紹介画像①": "",
  "企業紹介画像②": "",
  "企業紹介画像③": "",
  "届出・認定情報": "",
  "セールスポイント": "",
  "企業ホームページ": "http://www.kunmeido.jp",
  "店舗・事業所情報": "[]",
  "主な商品・サービス": "",
  "他社との連携を考える事業": ""
}