{
  "住所": "大阪府堺市堺区一条通８番１９号",
  "Twitter": "",
  "Facebook": "https://www.facebook.com/otsukakogei.osaka.sakai",
  "Instagram": "https://www.instagram.com/otsuka.kogei_osaka/?hl=ja",
  "創業年": "1968年",
  "法人名": "株式会社おおつか工芸",
  "紹介文": "昭和48年の創業以来、看板製作に情熱を注ぎ続けてきました。\nその経験と実績を活かし、個性豊かな精鋭スタッフとともにお客様満足度NO.1の看板屋を目指します。\n小さなステッカーから大きな看板まで、様々なsignをお手伝いいたします。",
  "アイコン": "https://img.sakacil.com/data/20220105/e2743c57-4bb0-4273-98f4-9f9a00a59beb.png",
  "事業概要": "堺市を拠点とし、看板や垂幕、プレートの製作から車体ラッピングに至るまで様々なニーズにお応えしています。\nロードサインも展開しており、まちのあらゆるサインに携わっております。",
  "代表者名": "大塚義則",
  "取扱商品": "店舗看板、屋外広告看板\nネームプレート、懸垂幕、ステッカー、車体ラッピング、箱文字、FRP造形など",
  "営業品目": "0799",
  "従業員数": "6",
  "採用予定": "予定有り",
  "更新日時": "2022-01-05T05:40:56.678+00:00",
  "法人番号": "9120101001249",
  "特許情報": "",
  "背景画像": "https://img.sakacil.com/data/20220105/51a2cbff-caa7-4845-8a2a-20f8e1bc5e4f.jpg",
  "表彰情報": "",
  "電話番号": "072-238-0101",
  "代表の写真": "",
  "取引先業種": "",
  "設備と技術": "",
  "設立年月日": "1986-08-01",
  "法人名(カナ)": "オオツカコウゲイ",
  "企業規模詳細": "",
  "キャッチコピー": "イメージをカタチに",
  "企業紹介画像①": "https://img.sakacil.com/data/20220105/0f7f0d52-b1e4-4011-8c06-4ba365be752f.jpg",
  "企業紹介画像②": "https://img.sakacil.com/data/20220105/cfa49fde-e018-44b6-ba40-d467019b5db4.jpg",
  "企業紹介画像③": "https://img.sakacil.com/data/20220105/0a070aed-71dc-49c1-a2d6-67b1b083916b.jpg",
  "届出・認定情報": "鋼構造物工事業、屋外広告業",
  "セールスポイント": "",
  "企業ホームページ": "",
  "店舗・事業所情報": "[]",
  "主な商品・サービス": "",
  "他社との連携を考える事業": ""
}