{
  "住所": "大阪府堺市美原区太井４６１番地１９",
  "Twitter": "",
  "Facebook": "",
  "Instagram": "https://www.instagram.com/tanibun.osaka/",
  "創業年": "1986年",
  "法人名": "株式会社谷文建設",
  "紹介文": "親身になって、お客様のお気持ちをくんで着工から完成まで出来る限り御要望にお答え、全力で取り組んでいます。",
  "アイコン": "https://img.sakacil.com/data/20211209/242b2b5e-3ad8-406b-b694-38bf33e87e09.jpeg",
  "事業概要": "新築住宅、店舗・住宅リフォーム、\n 耐震補強、公共工事業、外構工事業、解体工事業 等\n設計、施工、監理業務",
  "代表者名": "谷口　文夫",
  "取扱商品": "",
  "営業品目": "0651",
  "従業員数": "13人",
  "採用予定": "予定有り",
  "更新日時": "2021-12-09T10:00:12.146+00:00",
  "法人番号": "9120101004796",
  "特許情報": "",
  "背景画像": "https://img.sakacil.com/data/20211209/d122ff37-f34c-479c-bc3d-b52f42338bba.jpeg",
  "表彰情報": "",
  "電話番号": "072−369−1820",
  "代表の写真": "",
  "取引先業種": "住友林業株式会社、官公庁、民間",
  "設備と技術": "",
  "設立年月日": "1996-07-18",
  "法人名(カナ)": "タニブンケンセツ",
  "企業規模詳細": "男性：10名、女性：3名",
  "キャッチコピー": "お客様と寄り添い、確かな技術と情熱を持って夢をカタチに",
  "企業紹介画像①": "https://img.sakacil.com/data/20211209/62f92c4e-b722-44ae-bf03-b9001578a729.jpeg",
  "企業紹介画像②": "https://img.sakacil.com/data/20211209/6c783b04-28bb-4f0d-bdfa-28fbb7c240cf.jpeg",
  "企業紹介画像③": "https://img.sakacil.com/data/20211209/122f8d37-635e-4cf2-ba6f-1cff89a8899e.jpeg",
  "届出・認定情報": "特定建設業　建築工事業　大阪府知事許可　（特−3）102876号",
  "セールスポイント": "『任せてよかった』と言って頂けるTANIBUNの家づくり。",
  "企業ホームページ": "http://tanibun.co.jp/",
  "店舗・事業所情報": "[]",
  "主な商品・サービス": "",
  "他社との連携を考える事業": "不動産業、建設業等"
}