{
  "住所": "大阪府堺市北区野遠町３４３番地",
  "Twitter": "",
  "Facebook": "",
  "Instagram": "",
  "創業年": "",
  "法人名": "株式会社ペレボルサ",
  "紹介文": "",
  "アイコン": "",
  "事業概要": "ハンドバック製造、卸・小売\nオリジナルブランド「ペレボルサ」のハンドバッグ、小物の製造",
  "代表者名": "坂本　恭敏",
  "取扱商品": "ハンドバック・革小物",
  "営業品目": null,
  "従業員数": "120人",
  "採用予定": "",
  "更新日時": "2021-11-23T19:29:43.091+00:00",
  "法人番号": "9120101009309",
  "特許情報": "",
  "背景画像": "",
  "表彰情報": "",
  "電話番号": "072-252-2503",
  "代表の写真": "",
  "取引先業種": "百貨店、ハンドバッグ専門店、通販、ＴＶ通販",
  "設備と技術": "皮革、袋物加工技術(裁断、漉き、墨塗、縫製)、それらに必要な設備を保有",
  "設立年月日": "",
  "法人名(カナ)": "",
  "企業規模詳細": "",
  "キャッチコピー": "",
  "企業紹介画像①": "",
  "企業紹介画像②": "",
  "企業紹介画像③": "",
  "届出・認定情報": "",
  "セールスポイント": "弊社工場では自社ブランド「ペレボルサ」のサンプル作成から資材調達～組立完成までを一貫して行っています。様々な商品を通して確かな品質とオリジナリティーあふれる弊社のものづくりを堺から日本全国・世界各国に向けて、積極的に発信しております。",
  "企業ホームページ": "www.pelle-borsa.com",
  "店舗・事業所情報": [],
  "主な商品・サービス": "ハンドバッグ・革小物",
  "他社との連携を考える事業": ""
}